[
    {
        "name": "doctor_id",
        "dbType": "integer,true",
        "htmlType": "number",
        "validations": "",
        "searchable": false,
        "fillable": false,
        "primary": true,
        "inForm": false,
        "inIndex": false,
        "inView": false
    },
    {
        "name": "user_id",
        "dbType": "integer,false",
        "htmlType": "number",
        "validations": "nullable|nullable",
        "searchable": true,
        "fillable": true,
        "primary": false,
        "inForm": true,
        "inIndex": true,
        "inView": true
    },
    {
        "name": "specialization_id",
        "dbType": "integer,false",
        "htmlType": "number",
        "validations": "nullable|nullable",
        "searchable": true,
        "fillable": true,
        "primary": false,
        "inForm": true,
        "inIndex": true,
        "inView": true
    },
    {
        "name": "location_id",
        "dbType": "integer,false",
        "htmlType": "number",
        "validations": "nullable|nullable",
        "searchable": true,
        "fillable": true,
        "primary": false,
        "inForm": true,
        "inIndex": true,
        "inView": true
    },
    {
        "name": "experience_years",
        "dbType": "integer,false",
        "htmlType": "number",
        "validations": "nullable|nullable",
        "searchable": true,
        "fillable": true,
        "primary": false,
        "inForm": true,
        "inIndex": true,
        "inView": true
    },
    {
        "name": "mdcn_license",
        "dbType": "string",
        "htmlType": "text",
        "validations": "nullable|string|max:100|nullable|string|max:100",
        "searchable": true,
        "fillable": true,
        "primary": false,
        "inForm": true,
        "inIndex": true,
        "inView": true
    },
    {
        "name": "cpd_annual_license",
        "dbType": "string",
        "htmlType": "text",
        "validations": "nullable|string|max:100|nullable|string|max:100",
        "searchable": true,
        "fillable": true,
        "primary": false,
        "inForm": true,
        "inIndex": true,
        "inView": true
    },
    {
        "name": "bank_details",
        "dbType": "string",
        "htmlType": "text",
        "validations": "nullable|string|max:255|nullable|string|max:255",
        "searchable": true,
        "fillable": true,
        "primary": false,
        "inForm": true,
        "inIndex": true,
        "inView": true
    },
    {
        "type": "relation",
        "relation": "mt1,Specialization,specialization_id"
    },
    {
        "type": "relation",
        "relation": "mt1,Location,location_id"
    },
    {
        "type": "relation",
        "relation": "mt1,User,user_id"
    },
    {
        "type": "relation",
        "relation": "mtm,User,appointments"
    },
    {
        "type": "relation",
        "relation": "mtm,User,consents"
    },
    {
        "type": "relation",
        "relation": "mtm,Patient,medical_records"
    },
    {
        "type": "relation",
        "relation": "mtm,User,prescriptions"
    },
    {
        "type": "relation",
        "relation": "mtm,User,reviews"
    },
    {
        "type": "relation",
        "relation": "mtm,Patient,treatment_plans"
    }
]